grpphati_rs-0.3.1.dist-info/METADATA
grpphati_rs-0.3.1.dist-info/WHEEL
grpphati_rs-0.3.1.dist-info/license_files/LICENSE
grpphati_rs/dflag.py
grpphati_rs/pipelines.py
grpphati_rs/__init__.py
grpphati_rs/rrph.py
grpphati_rs/sparsifier.py
grpphati_rs/grpphati_rs.pypy37-pp73-s390x-linux-gnu.so
grpphati_rs-0.3.1.dist-info/RECORD
