Metadata-Version: 2.1
Name: grpphati_rs
Version: 0.3.1
Classifier: Programming Language :: Rust
Classifier: Programming Language :: Python :: Implementation :: CPython
Classifier: Programming Language :: Python :: Implementation :: PyPy
Requires-Dist: grpphati==0.4.1
License-File: LICENSE
Requires-Python: >=3.7
